piano_visualizer/__init__.py
piano_visualizer-1.1.0.dist-info/LICENSE
piano_visualizer-1.1.0.dist-info/METADATA
piano_visualizer-1.1.0.dist-info/WHEEL
piano_visualizer-1.1.0.dist-info/top_level.txt
piano_visualizer-1.1.0.dist-info/RECORD
