Metadata-Version: 2.1
Name: piano-visualizer
Version: 1.1.0
Summary: A python library that allows you to export a video in which a piano is playing the music you give it.
Home-page: https://github.com/ArjunSahlot/piano_visualizer
Author: Arjun Sahlot
Author-email: iarjun.sahlot@gmail.com
License: GNU GPL v3
Keywords: piano,visualizer
Platform: UNKNOWN
Classifier: Programming Language :: Python :: 3
Classifier: Intended Audience :: Developers
Classifier: Topic :: Software Development :: Build Tools
Classifier: License :: OSI Approved :: GNU General Public License v3 (GPLv3)
Classifier: Operating System :: OS Independent
Requires-Python: >=3
License-File: LICENSE
Requires-Dist: ffmpeg-python
Requires-Dist: midi2audio
Requires-Dist: mido
Requires-Dist: notify-py
Requires-Dist: opencv-python
Requires-Dist: pydub
Requires-Dist: pygame
Requires-Dist: random-utils
Requires-Dist: tqdm
